README.rst
setup.py
xfw.py
xfw.egg-info/PKG-INFO
xfw.egg-info/SOURCES.txt
xfw.egg-info/dependency_links.txt
xfw.egg-info/top_level.txt
xfw.egg-info/zip-safe