Metadata-Version: 1.1
Name: xfw
Version: 0.10
Summary: eXtensible Fixed-Width file handling module
Home-page: http://git.erp5.org/gitweb/xfw.git
Author: Nexedi
Author-email: erp5-dev@erp5.org
License: GPL 2+
Keywords: fixed width field file
Platform: any
Classifier: Intended Audience :: Developers
Classifier: License :: OSI Approved :: GNU General Public License (GPL)
Classifier: Operating System :: OS Independent
Classifier: Programming Language :: Python :: 2.7
Classifier: Programming Language :: Python :: Implementation :: PyPy
Classifier: Programming Language :: Python :: Implementation :: CPython
